{"token":"xyt9xRFxvmjedZmKKev7yGqztzU6qQkqJhp3mGDe","title":"learn anything - programming - software development - architectural patterns - flux","backgroundColor":"rgba(243, 246, 243, 1.0)","nodes":[{"allowNodeStrokeColorVariants":false,"decreasingStrokeWidth":true,"foldedSubnodes":false,"isLeftAligned":false,"id":"B6BB6D40-C59C-4CC3-A2E2-4A561C6A032C","pathStyle":{"lineType":"curved","strokeStyle":{"color":"rgba(21, 122, 150, 1.0)","dash":null,"width":4}},"shapeStyle":{"fillColor":"rgba(255, 255, 255, 1.0)","shapeType":"roundedrect","borderStrokeStyle":{"color":"rgba(246, 246, 246, 1.0)","dash":null,"width":2}},"image":null,"title":{"allowToShrinkWidth":true,"maxWidth":300,"text":"<p style='color: rgba(22, 103, 132, 1.000000); font: 21px \"Helvetica Neue\"; text-align: center;  '><a rel=\"nofollow\">Flux architecture</a></p>","fontStyle":null},"note":null,"noteIndicatorColor":"rgba(0, 0, 0, 1.0)","nodes":[],"location":{"x":5.74609375,"y":-152.60546875},"layoutStyle":"defaultright","task":null},{"allowNodeStrokeColorVariants":false,"decreasingStrokeWidth":true,"foldedSubnodes":false,"isLeftAligned":false,"id":"DA7D96F8-352F-44E8-9BC2-3B4F778904DF","pathStyle":{"lineType":"curved","strokeStyle":{"color":"rgba(21, 122, 150, 1.0)","dash":null,"width":4}},"shapeStyle":{"fillColor":"rgba(255, 255, 255, 1.0)","shapeType":"roundedrect","borderStrokeStyle":{"color":"rgba(246, 246, 246, 1.0)","dash":null,"width":2}},"image":null,"title":{"allowToShrinkWidth":true,"maxWidth":300,"text":"<p style='color: rgba(22, 103, 132, 1.000000); font: 21px \"Helvetica Neue\"; text-align: center;  '>basics</p>","fontStyle":null},"note":null,"noteIndicatorColor":"rgba(0, 0, 0, 1.0)","nodes":[{"allowNodeStrokeColorVariants":false,"decreasingStrokeWidth":false,"foldedSubnodes":false,"isLeftAligned":false,"id":"16DF5C34-2402-4204-A9CC-3C6075721503","pathStyle":{"lineType":"curved","strokeStyle":{"color":"rgba(175, 54, 242, 1.0)","dash":null,"width":6}},"shapeStyle":{"fillColor":"rgba(255, 255, 255, 1.0)","shapeType":null,"borderStrokeStyle":{"color":"rgba(175, 54, 242, 1.0)","dash":null,"width":2}},"image":null,"title":{"allowToShrinkWidth":true,"maxWidth":300,"text":"<p style=\"text-align: left; \"><a style='color: rgba(72, 72, 72, 1.000000); font: 18px \"Helvetica Neue\";  ' href=\"https://scotch.io/tutorials/getting-to-know-flux-the-react-js-architecture\" rel=\"nofollow\">1. introduction </a><a style='color: rgba(72, 72, 72, 1.000000); font: 18px \"Apple Color Emoji\";  ' href=\"https://scotch.io/tutorials/getting-to-know-flux-the-react-js-architecture\" rel=\"nofollow\">🖋️</a></p>","fontStyle":null},"note":null,"noteIndicatorColor":"rgba(0, 0, 0, 1.0)","nodes":[],"location":{"x":202.12070009689637,"y":6.218628875955119},"layoutStyle":"manual","task":null}],"location":{"x":46.12070009689637,"y":-5.281371124044881},"layoutStyle":"defaultright","task":null}],"connections":[{"endNodeID":"DA7D96F8-352F-44E8-9BC2-3B4F778904DF","startNodeID":"B6BB6D40-C59C-4CC3-A2E2-4A561C6A032C","pathStyle":{"lineType":"curved","strokeStyle":{"color":"rgba(254, 90, 46, 1.0)","dash":[5,2],"width":2}},"arrowStyle":{"startArrow":null,"endArrow":"trianglefilled"},"title":{"allowToShrinkWidth":true,"maxWidth":250,"text":"","fontStyle":{"bold":false,"italic":false,"underline":false,"strikethrough":false,"color":"rgba(255, 255, 255, 1.0)","fontName":"HelveticaNeue","fontSize":14,"alignment":"center"}},"wayPointOffset":{"x":-2.5627,"y":73.662}}],"ready":true,"trigger":"Flux software architecture"}