{
  "title": "learn anything - life - meaning of life",
  "tag": "",
  "nodes": [
    {
      "text": "meaning of life",
      "url": "http://www.wikiwand.com/en/Meaning_of_life",
      "fx": 154.36923599243164,
      "fy": -166.69513287990213,
      "category": "wiki"
    },
    {
      "text": "basics",
      "url": "",
      "fx": 204.50514796052778,
      "fy": -20.204486727101596
    },
    {
      "text": "happiness  ️",
      "url": "https://my.mindnode.com/yDzksCE9TATPeVb3HyAsTJSsRtqQXyQ8xV1Ydinc",
      "fx": -21.166760781974972,
      "fy": 109.09413008105241,
      "category": "mindmap"
    },
    {
      "text": "love  ️",
      "url": "https://my.mindnode.com/wySoJKK7pmtZKoDinECyELqjAfgAVqtyN3qz8ANd",
      "fx": 190.2563302568392,
      "fy": 111.4495543884716,
      "category": "mindmap"
    }
  ],
  "subnodes": [
    {
      "text": "1. Alan Watts - the secret of life",
      "url": "https://www.youtube.com/watch?v=iZ8so-ld-l0",
      "fx": 360.5051479605278,
      "fy": -90.7044867271016,
      "category": "video",
      "color": "rgba(175, 54, 242, 1.0)",
      "parent": "basics"
    },
    {
      "text": "1. Alan Watts - is there a purpose to living?",
      "url": "https://www.youtube.com/watch?v=21RwqnB8GrE",
      "fx": 360.5051479605278,
      "fy": -50.704486727101596,
      "category": "video",
      "color": "rgba(36, 170, 255, 1.0)",
      "parent": "basics"
    },
    {
      "text": "1. it’s just a ride",
      "url": "https://www.youtube.com/watch?v=KgzQuE1pR1w",
      "fx": 360.5051479605278,
      "fy": 11.295513272898404,
      "category": "video",
      "color": "rgba(255, 189, 10, 1.0)",
      "parent": "basics"
    },
    {
      "text": "1. Alan Watts - does life have a meaning?",
      "url": "https://www.youtube.com/watch?v=l5vbmY0YwTs",
      "fx": 360.5051479605278,
      "fy": 51.295513272898404,
      "category": "video",
      "color": "rgba(34, 205, 224, 1.0)",
      "parent": "basics"
    }
  ],
  "connections": [
    {
      "source": "meaning of life",
      "target": "basics",
      "curve": {
        "x": -0.432047,
        "y": 71.9953
      }
    },
    {
      "source": "basics",
      "target": "happiness  ️",
      "curve": {
        "x": -104.086,
        "y": 64.6493
      }
    },
    {
      "source": "basics",
      "target": "love  ️",
      "curve": {
        "x": -5.12444,
        "y": 67.077
      }
    }
  ]
}