{"token":"hzAsvpveCknTvxZuRpbtxm4Uh4bxqzeGaxqqgMp8","title":"learn anything - security - authentication - passwords","backgroundColor":"rgba(243, 246, 243, 1.0)","nodes":[{"allowNodeStrokeColorVariants":false,"decreasingStrokeWidth":true,"foldedSubnodes":false,"isLeftAligned":false,"id":"44BFCE69-3A7C-4015-B031-0DA83CE8080F","pathStyle":{"lineType":"curved","strokeStyle":{"color":"rgba(21, 122, 150, 1.0)","dash":null,"width":4}},"shapeStyle":{"fillColor":"rgba(255, 255, 255, 1.0)","shapeType":"roundedrect","borderStrokeStyle":{"color":"rgba(246, 246, 246, 1.0)","dash":null,"width":2}},"image":null,"title":{"allowToShrinkWidth":true,"maxWidth":300,"text":"<p style=\"text-align: center; \"><a style='color: rgba(22, 103, 132, 1.000000); font: 21px \"Helvetica Neue\";  ' href=\"http://www.wikiwand.com/en/Password\" rel=\"nofollow\">passwords </a><a style='color: rgba(22, 103, 132, 1.000000); font: 21px \"Apple Color Emoji\";  ' href=\"http://www.wikiwand.com/en/Password\" rel=\"nofollow\">🌐</a></p>","fontStyle":null},"note":null,"noteIndicatorColor":"rgba(0, 0, 0, 1.0)","nodes":[],"location":{"x":-77.62517197327043,"y":-472.3142688679246},"layoutStyle":"defaultright","task":null},{"allowNodeStrokeColorVariants":false,"decreasingStrokeWidth":true,"foldedSubnodes":false,"isLeftAligned":false,"id":"BF1B3C29-06CD-4976-AE87-DFCD7DFA4350","pathStyle":{"lineType":"curved","strokeStyle":{"color":"rgba(21, 122, 150, 1.0)","dash":null,"width":4}},"shapeStyle":{"fillColor":"rgba(255, 255, 255, 1.0)","shapeType":"roundedrect","borderStrokeStyle":{"color":"rgba(246, 246, 246, 1.0)","dash":null,"width":2}},"image":null,"title":{"allowToShrinkWidth":true,"maxWidth":300,"text":"<p style='color: rgba(22, 103, 132, 1.000000); font: 21px \"Helvetica Neue\"; text-align: center;  '>tools</p>","fontStyle":null},"note":null,"noteIndicatorColor":"rgba(0, 0, 0, 1.0)","nodes":[{"allowNodeStrokeColorVariants":false,"decreasingStrokeWidth":false,"foldedSubnodes":false,"isLeftAligned":false,"id":"73CE5323-549B-465B-91E3-D9D11BC3C43F","pathStyle":{"lineType":"curved","strokeStyle":{"color":"rgba(175, 54, 242, 1.0)","dash":null,"width":6}},"shapeStyle":{"fillColor":"rgba(255, 255, 255, 1.0)","shapeType":null,"borderStrokeStyle":{"color":"rgba(175, 54, 242, 1.0)","dash":null,"width":2}},"image":null,"title":{"allowToShrinkWidth":true,"maxWidth":300,"text":"<p style='color: rgba(72, 72, 72, 1.000000); font: 18px \"Helvetica Neue\"; text-align: left;  '><a href=\"https://howsecureismypassword.net/\" rel=\"nofollow\">how secure is my password?</a></p>","fontStyle":null},"note":null,"noteIndicatorColor":"rgba(0, 0, 0, 1.0)","nodes":[],"location":{"x":196.40240205223893,"y":-355.10296175373134},"layoutStyle":"manual","task":null}],"location":{"x":55.402402052238926,"y":-369.60296175373134},"layoutStyle":"defaultright","task":null},{"allowNodeStrokeColorVariants":false,"decreasingStrokeWidth":true,"foldedSubnodes":false,"isLeftAligned":false,"id":"4EFD97B1-0F6F-4E4E-93AB-5A563F2C6BD1","pathStyle":{"lineType":"curved","strokeStyle":{"color":"rgba(21, 122, 150, 1.0)","dash":null,"width":4}},"shapeStyle":{"fillColor":"rgba(255, 255, 255, 1.0)","shapeType":"roundedrect","borderStrokeStyle":{"color":"rgba(246, 246, 246, 1.0)","dash":null,"width":2}},"image":null,"title":{"allowToShrinkWidth":true,"maxWidth":300,"text":"<p style='color: rgba(22, 103, 132, 1.000000); font: 21px \"Helvetica Neue\"; text-align: center;  '>basics</p>","fontStyle":null},"note":null,"noteIndicatorColor":"rgba(0, 0, 0, 1.0)","nodes":[{"allowNodeStrokeColorVariants":false,"decreasingStrokeWidth":false,"foldedSubnodes":false,"isLeftAligned":false,"id":"E2DA5D77-5F98-47BC-B793-093F74107298","pathStyle":{"lineType":"curved","strokeStyle":{"color":"rgba(175, 54, 242, 1.0)","dash":null,"width":6}},"shapeStyle":{"fillColor":"rgba(255, 255, 255, 1.0)","shapeType":null,"borderStrokeStyle":{"color":"rgba(175, 54, 242, 1.0)","dash":null,"width":2}},"image":null,"title":{"allowToShrinkWidth":true,"maxWidth":300,"text":"<p style=\"text-align: left; \"><a style='color: rgba(72, 72, 72, 1.000000); font: 18px \"Helvetica Neue\";  ' href=\"https://www.youtube.com/watch?v=3NjQ9b3pgIg\" rel=\"nofollow\">1. how to choose a password </a><a style='color: rgba(72, 72, 72, 1.000000); font: 18px \"Apple Color Emoji\";  ' href=\"https://www.youtube.com/watch?v=3NjQ9b3pgIg\" rel=\"nofollow\">👀</a></p>","fontStyle":null},"note":null,"noteIndicatorColor":"rgba(0, 0, 0, 1.0)","nodes":[],"location":{"x":107.07421875,"y":-264.64453125},"layoutStyle":"manual","task":null}],"location":{"x":-48.92578125,"y":-276.14453125},"layoutStyle":"defaultright","task":null},{"allowNodeStrokeColorVariants":false,"decreasingStrokeWidth":true,"foldedSubnodes":false,"isLeftAligned":false,"id":"67D13D29-11EF-4F3A-B5F1-A735732A13A2","pathStyle":{"lineType":"curved","strokeStyle":{"color":"rgba(21, 122, 150, 1.0)","dash":null,"width":4}},"shapeStyle":{"fillColor":"rgba(255, 255, 255, 1.0)","shapeType":"roundedrect","borderStrokeStyle":{"color":"rgba(246, 246, 246, 1.0)","dash":null,"width":2}},"image":null,"title":{"allowToShrinkWidth":true,"maxWidth":300,"text":"<p style=\"text-align: center; \"><a style='color: rgba(22, 103, 132, 1.000000); font: 21px \"Helvetica Neue\";  ' href=\"http://www.wikiwand.com/en/Password_manager\" rel=\"nofollow\">password managers </a><a style='color: rgba(22, 103, 132, 1.000000); font: 21px \"Apple Color Emoji\";  ' href=\"http://www.wikiwand.com/en/Password_manager\" rel=\"nofollow\">🌐</a></p>","fontStyle":null},"note":null,"noteIndicatorColor":"rgba(0, 0, 0, 1.0)","nodes":[],"location":{"x":-21.513457216757274,"y":-132.52800097526972},"layoutStyle":"defaultright","task":null},{"allowNodeStrokeColorVariants":false,"decreasingStrokeWidth":true,"foldedSubnodes":false,"isLeftAligned":false,"id":"6C6D2B19-992E-412F-A916-ED5495E43B61","pathStyle":{"lineType":"curved","strokeStyle":{"color":"rgba(21, 122, 150, 1.0)","dash":null,"width":4}},"shapeStyle":{"fillColor":"rgba(255, 255, 255, 1.0)","shapeType":"roundedrect","borderStrokeStyle":{"color":"rgba(246, 246, 246, 1.0)","dash":null,"width":2}},"image":null,"title":{"allowToShrinkWidth":true,"maxWidth":300,"text":"<p style=\"text-align: center; \"><a style='color: rgba(22, 103, 132, 1.000000); font: 21px \"Helvetica Neue\";  ' href=\"/id/c6yHRBsDdxxfwS9G6JjUosBYs8AVapgkmsRk14yz\" rel=\"nofollow\">password cracking </a><a style='color: rgba(22, 103, 132, 1.000000); font: 21px \"Apple Color Emoji\";  ' href=\"/id/c6yHRBsDdxxfwS9G6JjUosBYs8AVapgkmsRk14yz\" rel=\"nofollow\">🗺️</a></p>","fontStyle":null},"note":null,"noteIndicatorColor":"rgba(0, 0, 0, 1.0)","nodes":[],"location":{"x":-289.7498306156223,"y":-129.4390715223621},"layoutStyle":"defaultright","task":null},{"allowNodeStrokeColorVariants":false,"decreasingStrokeWidth":true,"foldedSubnodes":false,"isLeftAligned":false,"id":"CDE53FED-03AA-4919-9D10-3801FFD903C3","pathStyle":{"lineType":"curved","strokeStyle":{"color":"rgba(21, 122, 150, 1.0)","dash":null,"width":4}},"shapeStyle":{"fillColor":"rgba(255, 255, 255, 1.0)","shapeType":"roundedrect","borderStrokeStyle":{"color":"rgba(246, 246, 246, 1.0)","dash":null,"width":2}},"image":null,"title":{"allowToShrinkWidth":true,"maxWidth":300,"text":"<p style='color: rgba(22, 103, 132, 1.000000); font: 21px \"Helvetica Neue\"; text-align: center;  '><a href=\"https://www.dashlane.com/\" rel=\"nofollow\">Dashlane</a></p>","fontStyle":null},"note":null,"noteIndicatorColor":"rgba(0, 0, 0, 1.0)","nodes":[],"location":{"x":85.55780410766602,"y":35.19283413887024},"layoutStyle":"defaultright","task":null},{"allowNodeStrokeColorVariants":false,"decreasingStrokeWidth":true,"foldedSubnodes":false,"isLeftAligned":false,"id":"EFCC0B20-3B2D-4259-9CDC-5406BC84B1C6","pathStyle":{"lineType":"curved","strokeStyle":{"color":"rgba(21, 122, 150, 1.0)","dash":null,"width":4}},"shapeStyle":{"fillColor":"rgba(255, 255, 255, 1.0)","shapeType":"roundedrect","borderStrokeStyle":{"color":"rgba(246, 246, 246, 1.0)","dash":null,"width":2}},"image":null,"title":{"allowToShrinkWidth":true,"maxWidth":300,"text":"<p style='color: rgba(22, 103, 132, 1.000000); font: 21px \"Helvetica Neue\"; text-align: center;  '><a href=\"http://keepass.info/\" rel=\"nofollow\">KeePass</a></p>","fontStyle":null},"note":null,"noteIndicatorColor":"rgba(0, 0, 0, 1.0)","nodes":[],"location":{"x":224.12637778482213,"y":36.78735097266656},"layoutStyle":"defaultright","task":null},{"allowNodeStrokeColorVariants":false,"decreasingStrokeWidth":true,"foldedSubnodes":false,"isLeftAligned":false,"id":"95250D32-8590-45B8-B75C-2FBCDFF445C4","pathStyle":{"lineType":"curved","strokeStyle":{"color":"rgba(21, 122, 150, 1.0)","dash":null,"width":4}},"shapeStyle":{"fillColor":"rgba(255, 255, 255, 1.0)","shapeType":"roundedrect","borderStrokeStyle":{"color":"rgba(246, 246, 246, 1.0)","dash":null,"width":2}},"image":null,"title":{"allowToShrinkWidth":true,"maxWidth":300,"text":"<p style='color: rgba(22, 103, 132, 1.000000); font: 21px \"Helvetica Neue\"; text-align: center;  '><a href=\"https://www.lastpass.com/\" rel=\"nofollow\">LastPass</a></p>","fontStyle":null},"note":null,"noteIndicatorColor":"rgba(0, 0, 0, 1.0)","nodes":[],"location":{"x":-51.735589027404785,"y":37.00723145459165},"layoutStyle":"defaultright","task":null},{"allowNodeStrokeColorVariants":false,"decreasingStrokeWidth":true,"foldedSubnodes":false,"isLeftAligned":false,"id":"A5E671AE-0862-433C-85FE-CF78D1290E61","pathStyle":{"lineType":"curved","strokeStyle":{"color":"rgba(21, 122, 150, 1.0)","dash":null,"width":4}},"shapeStyle":{"fillColor":"rgba(255, 255, 255, 1.0)","shapeType":"roundedrect","borderStrokeStyle":{"color":"rgba(246, 246, 246, 1.0)","dash":null,"width":2}},"image":null,"title":{"allowToShrinkWidth":true,"maxWidth":300,"text":"<p style=\"text-align: center; \"><a style='color: rgba(22, 103, 132, 1.000000); font: 21px \"Helvetica Neue\";  ' href=\"https://github.com/justwatchcom/gopass\" rel=\"nofollow\">gopass </a><a style='color: rgba(22, 103, 132, 1.000000); font: 21px \"Apple Color Emoji\";  ' href=\"https://github.com/justwatchcom/gopass\" rel=\"nofollow\">🐙</a></p>","fontStyle":null},"note":null,"noteIndicatorColor":"rgba(0, 0, 0, 1.0)","nodes":[],"location":{"x":362.47633057675944,"y":36.73714482613127},"layoutStyle":"defaultright","task":null},{"allowNodeStrokeColorVariants":false,"decreasingStrokeWidth":true,"foldedSubnodes":false,"isLeftAligned":false,"id":"B13C7D80-C44A-4E20-A58C-E5348F2553FD","pathStyle":{"lineType":"curved","strokeStyle":{"color":"rgba(21, 122, 150, 1.0)","dash":null,"width":4}},"shapeStyle":{"fillColor":"rgba(255, 255, 255, 1.0)","shapeType":"roundedrect","borderStrokeStyle":{"color":"rgba(246, 246, 246, 1.0)","dash":null,"width":2}},"image":null,"title":{"allowToShrinkWidth":true,"maxWidth":300,"text":"<p style='color: rgba(22, 103, 132, 1.000000); font: 21px \"Helvetica Neue\"; text-align: center;  '><a href=\"https://1password.com/\" rel=\"nofollow\">1password</a></p>","fontStyle":null},"note":null,"noteIndicatorColor":"rgba(0, 0, 0, 1.0)","nodes":[],"location":{"x":-198.85049438476562,"y":39.49290108036348},"layoutStyle":"defaultright","task":null}],"connections":[{"endNodeID":"44BFCE69-3A7C-4015-B031-0DA83CE8080F","startNodeID":"BF1B3C29-06CD-4976-AE87-DFCD7DFA4350","pathStyle":{"lineType":"curved","strokeStyle":{"color":"rgba(254, 90, 46, 1.0)","dash":[5,2],"width":2}},"arrowStyle":{"startArrow":null,"endArrow":"trianglefilled"},"title":{"allowToShrinkWidth":true,"maxWidth":250,"text":"","fontStyle":{"bold":false,"italic":false,"underline":false,"strikethrough":false,"color":"rgba(255, 255, 255, 1.0)","fontName":"HelveticaNeue","fontSize":14,"alignment":"center"}},"wayPointOffset":{"x":-44.2638,"y":-50.1056}},{"endNodeID":"B13C7D80-C44A-4E20-A58C-E5348F2553FD","startNodeID":"67D13D29-11EF-4F3A-B5F1-A735732A13A2","pathStyle":{"lineType":"curved","strokeStyle":{"color":"rgba(254, 90, 46, 1.0)","dash":[5,2],"width":2}},"arrowStyle":{"startArrow":null,"endArrow":"trianglefilled"},"title":{"allowToShrinkWidth":true,"maxWidth":250,"text":"","fontStyle":{"bold":false,"italic":false,"underline":false,"strikethrough":false,"color":"rgba(255, 255, 255, 1.0)","fontName":"HelveticaNeue","fontSize":14,"alignment":"center"}},"wayPointOffset":{"x":-116.918,"y":84.7605}},{"endNodeID":"95250D32-8590-45B8-B75C-2FBCDFF445C4","startNodeID":"67D13D29-11EF-4F3A-B5F1-A735732A13A2","pathStyle":{"lineType":"curved","strokeStyle":{"color":"rgba(254, 90, 46, 1.0)","dash":[5,2],"width":2}},"arrowStyle":{"startArrow":null,"endArrow":"trianglefilled"},"title":{"allowToShrinkWidth":true,"maxWidth":250,"text":"","fontStyle":{"bold":false,"italic":false,"underline":false,"strikethrough":false,"color":"rgba(255, 255, 255, 1.0)","fontName":"HelveticaNeue","fontSize":14,"alignment":"center"}},"wayPointOffset":{"x":-47.8611,"y":83.5176}},{"endNodeID":"CDE53FED-03AA-4919-9D10-3801FFD903C3","startNodeID":"67D13D29-11EF-4F3A-B5F1-A735732A13A2","pathStyle":{"lineType":"curved","strokeStyle":{"color":"rgba(254, 90, 46, 1.0)","dash":[5,2],"width":2}},"arrowStyle":{"startArrow":null,"endArrow":"trianglefilled"},"title":{"allowToShrinkWidth":true,"maxWidth":250,"text":"","fontStyle":{"bold":false,"italic":false,"underline":false,"strikethrough":false,"color":"rgba(255, 255, 255, 1.0)","fontName":"HelveticaNeue","fontSize":14,"alignment":"center"}},"wayPointOffset":{"x":21.0356,"y":82.6104}},{"endNodeID":"EFCC0B20-3B2D-4259-9CDC-5406BC84B1C6","startNodeID":"67D13D29-11EF-4F3A-B5F1-A735732A13A2","pathStyle":{"lineType":"curved","strokeStyle":{"color":"rgba(254, 90, 46, 1.0)","dash":[5,2],"width":2}},"arrowStyle":{"startArrow":null,"endArrow":"trianglefilled"},"title":{"allowToShrinkWidth":true,"maxWidth":250,"text":"","fontStyle":{"bold":false,"italic":false,"underline":false,"strikethrough":false,"color":"rgba(255, 255, 255, 1.0)","fontName":"HelveticaNeue","fontSize":14,"alignment":"center"}},"wayPointOffset":{"x":89.3199,"y":83.4077}},{"endNodeID":"4EFD97B1-0F6F-4E4E-93AB-5A563F2C6BD1","startNodeID":"44BFCE69-3A7C-4015-B031-0DA83CE8080F","pathStyle":{"lineType":"curved","strokeStyle":{"color":"rgba(254, 90, 46, 1.0)","dash":[5,2],"width":2}},"arrowStyle":{"startArrow":null,"endArrow":"trianglefilled"},"title":{"allowToShrinkWidth":true,"maxWidth":250,"text":"","fontStyle":{"bold":false,"italic":false,"underline":false,"strikethrough":false,"color":"rgba(255, 255, 255, 1.0)","fontName":"HelveticaNeue","fontSize":14,"alignment":"center"}},"wayPointOffset":{"x":-3.1503,"y":96.8349}},{"endNodeID":"6C6D2B19-992E-412F-A916-ED5495E43B61","startNodeID":"4EFD97B1-0F6F-4E4E-93AB-5A563F2C6BD1","pathStyle":{"lineType":"curved","strokeStyle":{"color":"rgba(254, 90, 46, 1.0)","dash":[5,2],"width":2}},"arrowStyle":{"startArrow":null,"endArrow":"trianglefilled"},"title":{"allowToShrinkWidth":true,"maxWidth":250,"text":"","fontStyle":{"bold":false,"italic":false,"underline":false,"strikethrough":false,"color":"rgba(255, 255, 255, 1.0)","fontName":"HelveticaNeue","fontSize":14,"alignment":"center"}},"wayPointOffset":{"x":-84.662,"y":74.6027}},{"endNodeID":"67D13D29-11EF-4F3A-B5F1-A735732A13A2","startNodeID":"4EFD97B1-0F6F-4E4E-93AB-5A563F2C6BD1","pathStyle":{"lineType":"curved","strokeStyle":{"color":"rgba(254, 90, 46, 1.0)","dash":[5,2],"width":2}},"arrowStyle":{"startArrow":null,"endArrow":"trianglefilled"},"title":{"allowToShrinkWidth":true,"maxWidth":250,"text":"","fontStyle":{"bold":false,"italic":false,"underline":false,"strikethrough":false,"color":"rgba(255, 255, 255, 1.0)","fontName":"HelveticaNeue","fontSize":14,"alignment":"center"}},"wayPointOffset":{"x":52.7062,"y":73.0583}},{"endNodeID":"A5E671AE-0862-433C-85FE-CF78D1290E61","startNodeID":"67D13D29-11EF-4F3A-B5F1-A735732A13A2","pathStyle":{"lineType":"curved","strokeStyle":{"color":"rgba(254, 90, 46, 1.0)","dash":[5,2],"width":2}},"arrowStyle":{"startArrow":null,"endArrow":"trianglefilled"},"title":{"allowToShrinkWidth":true,"maxWidth":250,"text":"","fontStyle":{"bold":false,"italic":false,"underline":false,"strikethrough":false,"color":"rgba(255, 255, 255, 1.0)","fontName":"HelveticaNeue","fontSize":14,"alignment":"left"}},"wayPointOffset":{"x":188.33,"y":74.9147}}],"ready":true,"trigger":"passwords"}