{"token":"VK7fUGCzQLrwGs8wqjsyouAYEbFS4i2apWbRqaHq","title":"learn anything - biology - zoology - animals - amphibians","backgroundColor":"rgba(29, 26, 22, 1.0)","nodes":[{"allowNodeStrokeColorVariants":false,"decreasingStrokeWidth":true,"foldedSubnodes":false,"isLeftAligned":false,"id":"2A531BE2-927F-4571-8FB0-6D1391B13E66","pathStyle":{"lineType":"curved","strokeStyle":{"color":"rgba(244, 255, 226, 1.0)","dash":null,"width":4}},"shapeStyle":{"fillColor":"rgba(4, 4, 3, 1.0)","shapeType":"roundedrect","borderStrokeStyle":{"color":"rgba(29, 26, 22, 1.0)","dash":null,"width":2}},"image":null,"title":{"allowToShrinkWidth":true,"maxWidth":300,"text":"<p style=\"text-align: center; \"><a style='color: rgba(241, 255, 220, 1.000000); font: 24px \"Helvetica Neue\";  ' href=\"http://www.wikiwand.com/en/Amphibian\" rel=\"nofollow\">amphibians </a><a style='color: rgba(241, 255, 220, 1.000000); font: 24px \"Apple Color Emoji\";  ' href=\"http://www.wikiwand.com/en/Amphibian\" rel=\"nofollow\">🌐</a></p>","fontStyle":null},"note":null,"noteIndicatorColor":"rgba(0, 0, 0, 1.0)","nodes":[],"location":{"x":91.5703125,"y":-193.25},"layoutStyle":"defaultright","task":null},{"allowNodeStrokeColorVariants":false,"decreasingStrokeWidth":true,"foldedSubnodes":false,"isLeftAligned":false,"id":"92D5E5F9-E15F-4A55-8A36-DB311591ABAD","pathStyle":{"lineType":"curved","strokeStyle":{"color":"rgba(244, 255, 226, 1.0)","dash":null,"width":4}},"shapeStyle":{"fillColor":"rgba(4, 4, 3, 1.0)","shapeType":"pill","borderStrokeStyle":{"color":"rgba(29, 26, 22, 1.0)","dash":null,"width":2}},"image":null,"title":{"allowToShrinkWidth":true,"maxWidth":300,"text":"<p style='color: rgba(241, 255, 220, 1.000000); font: 24px \"Helvetica Neue\"; text-align: center;  '>basics</p>","fontStyle":null},"note":null,"noteIndicatorColor":"rgba(0, 0, 0, 1.0)","nodes":[{"allowNodeStrokeColorVariants":false,"decreasingStrokeWidth":false,"foldedSubnodes":false,"isLeftAligned":false,"id":"A3EC05AC-8EC3-454D-9A6B-47FFFDA23023","pathStyle":{"lineType":"curved","strokeStyle":{"color":"rgba(104, 255, 109, 1.0)","dash":null,"width":6}},"shapeStyle":{"fillColor":"rgba(29, 26, 22, 1.0)","shapeType":null,"borderStrokeStyle":{"color":"rgba(104, 255, 109, 1.0)","dash":null,"width":4}},"image":null,"title":{"allowToShrinkWidth":false,"maxWidth":313,"text":"<p style=\"text-align: left; \"><a style='color: rgba(255, 254, 216, 1.000000); font: 21px \"Helvetica Neue\";  ' href=\"https://www.youtube.com/watch?v=AkqK2jdbduQ\" rel=\"nofollow\">1. the evolution of amphibians </a><a style='color: rgba(255, 254, 216, 1.000000); font: 21px \"Apple Color Emoji\";  ' href=\"https://www.youtube.com/watch?v=AkqK2jdbduQ\" rel=\"nofollow\">👀</a></p>","fontStyle":null},"note":null,"noteIndicatorColor":"rgba(0, 0, 0, 1.0)","nodes":[],"location":{"x":290.91796875,"y":-35.23046875},"layoutStyle":"manual","task":null}],"location":{"x":127.91796875,"y":-47.73046875},"layoutStyle":"defaultright","task":null}],"connections":[{"endNodeID":"92D5E5F9-E15F-4A55-8A36-DB311591ABAD","startNodeID":"2A531BE2-927F-4571-8FB0-6D1391B13E66","pathStyle":{"lineType":"curved","strokeStyle":{"color":"rgba(144, 124, 104, 1.0)","dash":[5,2],"width":2}},"arrowStyle":{"startArrow":null,"endArrow":"trianglefilled"},"title":{"allowToShrinkWidth":true,"maxWidth":250,"text":"","fontStyle":{"bold":false,"italic":false,"underline":false,"strikethrough":false,"color":"rgba(255, 255, 255, 1.0)","fontName":"HelveticaNeue","fontSize":14,"alignment":"center"}},"wayPointOffset":{"x":-2.07617,"y":72.0098}}],"ready":true,"trigger":"amphibians"}