{"token":"5stN378JeNWspzs6M1aBpzKsSA2k5faXZpTbauV7","title":"learn anything - art - fashion","backgroundColor":"rgba(243, 246, 243, 1.0)","nodes":[{"allowNodeStrokeColorVariants":false,"decreasingStrokeWidth":true,"foldedSubnodes":false,"isLeftAligned":false,"id":"A369763C-3014-4251-A56E-79FDFFD85A44","pathStyle":{"lineType":"curved","strokeStyle":{"color":"rgba(21, 122, 150, 1.0)","dash":null,"width":4}},"shapeStyle":{"fillColor":"rgba(255, 255, 255, 1.0)","shapeType":"roundedrect","borderStrokeStyle":{"color":"rgba(246, 246, 246, 1.0)","dash":null,"width":2}},"image":null,"title":{"allowToShrinkWidth":true,"maxWidth":300,"text":"<p style=\"text-align: center; \"><a style='color: rgba(22, 103, 132, 1.000000); font: 21px \"Helvetica Neue\";  ' href=\"http://www.wikiwand.com/en/Fashion\" rel=\"nofollow\">fashion </a><a style='color: rgba(22, 103, 132, 1.000000); font: 21px \"Apple Color Emoji\";  ' href=\"http://www.wikiwand.com/en/Fashion\" rel=\"nofollow\">🌐</a></p>","fontStyle":null},"note":null,"noteIndicatorColor":"rgba(0, 0, 0, 1.0)","nodes":[{"allowNodeStrokeColorVariants":false,"decreasingStrokeWidth":false,"foldedSubnodes":false,"isLeftAligned":false,"id":"BBF66D96-FB0E-4DDA-B4A4-FEA77FD17E22","pathStyle":{"lineType":"curved","strokeStyle":{"color":"rgba(175, 54, 242, 1.0)","dash":null,"width":6}},"shapeStyle":{"fillColor":"rgba(255, 255, 255, 1.0)","shapeType":null,"borderStrokeStyle":{"color":"rgba(175, 54, 242, 1.0)","dash":null,"width":2}},"image":null,"title":{"allowToShrinkWidth":true,"maxWidth":300,"text":"<p style='color: rgba(72, 72, 72, 1.000000); font: 18px \"Apple Color Emoji\"; text-align: left;  '><a href=\"https://www.reddit.com/r/fashion/\" rel=\"nofollow\">🤖</a></p>","fontStyle":null},"note":null,"noteIndicatorColor":"rgba(0, 0, 0, 1.0)","nodes":[],"location":{"x":386.81024948559684,"y":-149.36514596193416},"layoutStyle":"manual","task":null},{"allowNodeStrokeColorVariants":false,"decreasingStrokeWidth":false,"foldedSubnodes":false,"isLeftAligned":false,"id":"56B6E5F7-0E33-4C37-9A93-BCF3F0923C85","pathStyle":{"lineType":"curved","strokeStyle":{"color":"rgba(255, 189, 10, 1.0)","dash":null,"width":6}},"shapeStyle":{"fillColor":"rgba(255, 255, 255, 1.0)","shapeType":null,"borderStrokeStyle":{"color":"rgba(255, 189, 10, 1.0)","dash":null,"width":2}},"image":null,"title":{"allowToShrinkWidth":true,"maxWidth":300,"text":"<p style=\"text-align: left; \"><a style='color: rgba(72, 72, 72, 1.000000); font: 18px \"Helvetica Neue\";  ' href=\"https://www.reddit.com/r/malefashionadvice/\" rel=\"nofollow\">male fashion advice </a><a style='color: rgba(72, 72, 72, 1.000000); font: 18px \"Apple Color Emoji\";  ' href=\"https://www.reddit.com/r/malefashionadvice/\" rel=\"nofollow\">🤖</a></p>","fontStyle":null},"note":null,"noteIndicatorColor":"rgba(0, 0, 0, 1.0)","nodes":[],"location":{"x":386.81024948559684,"y":-109.36514596193416},"layoutStyle":"manual","task":null}],"location":{"x":194.81024948559684,"y":-143.36514596193416},"layoutStyle":"defaultright","task":null},{"allowNodeStrokeColorVariants":false,"decreasingStrokeWidth":true,"foldedSubnodes":false,"isLeftAligned":false,"id":"CC812118-1B0B-4DEE-9412-C7066BA6953F","pathStyle":{"lineType":"curved","strokeStyle":{"color":"rgba(21, 122, 150, 1.0)","dash":null,"width":4}},"shapeStyle":{"fillColor":"rgba(255, 255, 255, 1.0)","shapeType":"roundedrect","borderStrokeStyle":{"color":"rgba(246, 246, 246, 1.0)","dash":null,"width":2}},"image":null,"title":{"allowToShrinkWidth":true,"maxWidth":300,"text":"<p style='color: rgba(22, 103, 132, 1.000000); font: 21px \"Helvetica Neue\"; text-align: center;  '>basics</p>","fontStyle":null},"note":null,"noteIndicatorColor":"rgba(0, 0, 0, 1.0)","nodes":[{"allowNodeStrokeColorVariants":false,"decreasingStrokeWidth":false,"foldedSubnodes":false,"isLeftAligned":false,"id":"2CCFF2E8-47BA-4DB4-8F3F-8B6DDBD83A44","pathStyle":{"lineType":"curved","strokeStyle":{"color":"rgba(175, 54, 242, 1.0)","dash":null,"width":6}},"shapeStyle":{"fillColor":"rgba(255, 255, 255, 1.0)","shapeType":null,"borderStrokeStyle":{"color":"rgba(175, 54, 242, 1.0)","dash":null,"width":2}},"image":null,"title":{"allowToShrinkWidth":false,"maxWidth":315,"text":"<p style=\"text-align: left; \"><a style='color: rgba(72, 72, 72, 1.000000); font: 18px \"Helvetica Neue\";  ' href=\"http://www.siamcostumes.com/cutters_guides/pdf/the_twentieth_century_(history_of_costume_and_fashion_volume_8).pdf\" rel=\"nofollow\">1. history of fashion and costume </a><a style='color: rgba(72, 72, 72, 1.000000); font: 18px \"Apple Color Emoji\";  ' href=\"http://www.siamcostumes.com/cutters_guides/pdf/the_twentieth_century_(history_of_costume_and_fashion_volume_8).pdf\" rel=\"nofollow\">📖</a></p>","fontStyle":null},"note":null,"noteIndicatorColor":"rgba(0, 0, 0, 1.0)","nodes":[],"location":{"x":363.10725767931274,"y":-21.800797325131725},"layoutStyle":"manual","task":null},{"allowNodeStrokeColorVariants":false,"decreasingStrokeWidth":false,"foldedSubnodes":false,"isLeftAligned":false,"id":"EC0B5DE1-D541-42DF-A1B2-DB1DDFBED00A","pathStyle":{"lineType":"curved","strokeStyle":{"color":"rgba(36, 170, 255, 1.0)","dash":null,"width":6}},"shapeStyle":{"fillColor":"rgba(255, 255, 255, 1.0)","shapeType":null,"borderStrokeStyle":{"color":"rgba(36, 170, 255, 1.0)","dash":null,"width":2}},"image":null,"title":{"allowToShrinkWidth":true,"maxWidth":300,"text":"<p style=\"text-align: left; \"><a style='color: rgba(73, 73, 73, 1.000000); font: 18px \"Helvetica Neue\";  ' href=\"http://www.goodreads.com/book/show/26786860-fashion\" rel=\"nofollow\">1. fashion: a history from the 18th to the 20th century  </a><a style='color: rgba(73, 73, 73, 1.000000); font: 18px \"Apple Color Emoji\";  ' href=\"http://www.goodreads.com/book/show/26786860-fashion\" rel=\"nofollow\">📕</a></p>","fontStyle":null},"note":null,"noteIndicatorColor":"rgba(0, 0, 0, 1.0)","nodes":[],"location":{"x":363.10725767931274,"y":18.199202674868275},"layoutStyle":"manual","task":null}],"location":{"x":207.10725767931274,"y":-2.3007973251317253},"layoutStyle":"defaultright","task":null},{"allowNodeStrokeColorVariants":false,"decreasingStrokeWidth":true,"foldedSubnodes":false,"isLeftAligned":false,"id":"FE195860-AB97-4FB5-A0FA-B97718077A16","pathStyle":{"lineType":"curved","strokeStyle":{"color":"rgba(21, 122, 150, 1.0)","dash":null,"width":4}},"shapeStyle":{"fillColor":"rgba(255, 255, 255, 1.0)","shapeType":"roundedrect","borderStrokeStyle":{"color":"rgba(246, 246, 246, 1.0)","dash":null,"width":2}},"image":null,"title":{"allowToShrinkWidth":true,"maxWidth":300,"text":"<p style=\"text-align: center; \"><a style='color: rgba(22, 103, 132, 1.000000); font: 21px \"Helvetica Neue\";  ' href=\"http://www.wikiwand.com/en/Fashion_design\" rel=\"nofollow\">fashion design </a><a style='color: rgba(22, 103, 132, 1.000000); font: 21px \"Apple Color Emoji\";  ' href=\"http://www.wikiwand.com/en/Fashion_design\" rel=\"nofollow\">🌐</a></p>","fontStyle":null},"note":null,"noteIndicatorColor":"rgba(0, 0, 0, 1.0)","nodes":[],"location":{"x":96.79659763313612,"y":144.5022189349114},"layoutStyle":"defaultright","task":null}],"connections":[{"endNodeID":"CC812118-1B0B-4DEE-9412-C7066BA6953F","startNodeID":"A369763C-3014-4251-A56E-79FDFFD85A44","pathStyle":{"lineType":"curved","strokeStyle":{"color":"rgba(254, 90, 46, 1.0)","dash":[5,2],"width":2}},"arrowStyle":{"startArrow":null,"endArrow":"trianglefilled"},"title":{"allowToShrinkWidth":true,"maxWidth":250,"text":"","fontStyle":{"bold":false,"italic":false,"underline":false,"strikethrough":false,"color":"rgba(255, 255, 255, 1.0)","fontName":"HelveticaNeue","fontSize":14,"alignment":"center"}},"wayPointOffset":{"x":-2.8515,"y":69.2822}},{"endNodeID":"FE195860-AB97-4FB5-A0FA-B97718077A16","startNodeID":"CC812118-1B0B-4DEE-9412-C7066BA6953F","pathStyle":{"lineType":"curved","strokeStyle":{"color":"rgba(254, 90, 46, 1.0)","dash":[5,2],"width":2}},"arrowStyle":{"startArrow":null,"endArrow":"trianglefilled"},"title":{"allowToShrinkWidth":true,"maxWidth":250,"text":"","fontStyle":{"bold":false,"italic":false,"underline":false,"strikethrough":false,"color":"rgba(255, 255, 255, 1.0)","fontName":"HelveticaNeue","fontSize":14,"alignment":"left"}},"wayPointOffset":{"x":-29.6553,"y":74.6515}}],"ready":true,"trigger":"fashion"}