{
  "title": "learn anything - physics - matter - atoms",
  "tag": "",
  "nodes": [
    {
      "text": "atoms",
      "url": "http://www.wikiwand.com/en/Atom",
      "fx": 7.573635101318359,
      "fy": -175.559232711792,
      "category": "wiki"
    },
    {
      "text": "basics",
      "url": "",
      "fx": 20.539306938648224,
      "fy": -28.054054975509644
    },
    {
      "text": "chemical bonds  ️",
      "url": "/physics/matter/atoms/chemical-bonds",
      "fx": -570.1552124023438,
      "fy": 117.81061172485352,
      "category": "mindmap"
    },
    {
      "text": "molecules  ️",
      "url": "/physics/matter/atoms/molecules",
      "fx": -333.03163146972656,
      "fy": 119.56588745117188,
      "category": "mindmap"
    },
    {
      "text": "atomic nucleus  ️",
      "url": "/physics/matter/atoms/atomic-nucleus",
      "fx": 119.06434599156114,
      "fy": 121.5158227848101,
      "category": "mindmap"
    },
    {
      "text": "subatomic particles  ️",
      "url": "/physics/matter/atoms/subatomic-particles",
      "fx": -152.93772411346436,
      "fy": 121.81510925292969,
      "category": "mindmap"
    }
  ],
  "subnodes": [
    {
      "text": "1. how small is an atom?",
      "url": "https://www.youtube.com/watch?v=_lNF3_30lUE",
      "fx": 183.53930693864822,
      "fy": -36.554054975509644,
      "category": "video",
      "color": "rgba(104, 255, 109, 1.0)",
      "parent": "basics"
    },
    {
      "text": "1. what are atoms?",
      "url": "https://www.youtube.com/watch?v=SggCE0kCJOY",
      "fx": 183.53930693864822,
      "fy": 5.4459450244903564,
      "category": "video",
      "color": "rgba(0, 224, 161, 1.0)",
      "parent": "basics"
    }
  ],
  "connections": [
    {
      "source": "atoms",
      "target": "basics",
      "curve": {
        "x": -0.517164,
        "y": 72.5026
      }
    },
    {
      "source": "basics",
      "target": "molecules  ️",
      "curve": {
        "x": -168.285,
        "y": 73.8099
      }
    },
    {
      "source": "basics",
      "target": "chemical bonds  ️",
      "curve": {
        "x": -292.222,
        "y": 57.3901
      }
    },
    {
      "source": "basics",
      "target": "subatomic particles  ️",
      "curve": {
        "x": -54.4885,
        "y": 74.9346
      }
    },
    {
      "source": "basics",
      "target": "atomic nucleus  ️",
      "curve": {
        "x": 70.7625,
        "y": 74.7849
      }
    }
  ]
}