{"token":"VpJdPJm5zGads7QqQNC4HRSuKVwyghD3DCWYumGf","title":"learn anything - operating systems - unix - macos - automation - keyboard maestro","backgroundColor":"rgba(29, 26, 22, 1.0)","nodes":[{"allowNodeStrokeColorVariants":false,"decreasingStrokeWidth":true,"foldedSubnodes":false,"isLeftAligned":false,"id":"90F2E8AB-06E9-4615-8FB1-EB46566DCB4E","pathStyle":{"lineType":"curved","strokeStyle":{"color":"rgba(244, 255, 226, 1.0)","dash":null,"width":4}},"shapeStyle":{"fillColor":"rgba(4, 4, 3, 1.0)","shapeType":"pill","borderStrokeStyle":{"color":"rgba(29, 26, 22, 1.0)","dash":null,"width":2}},"image":null,"title":{"allowToShrinkWidth":true,"maxWidth":300,"text":"<p style='color: rgba(241, 255, 220, 1.000000); font: 24px \"Helvetica Neue\"; text-align: center;  '><a href=\"https://www.keyboardmaestro.com/main/\" rel=\"nofollow\">keyboard maestro</a></p>","fontStyle":null},"note":null,"noteIndicatorColor":"rgba(0, 0, 0, 1.0)","nodes":[],"location":{"x":-112.5,"y":-226.78515625},"layoutStyle":"defaultright","task":null},{"allowNodeStrokeColorVariants":false,"decreasingStrokeWidth":true,"foldedSubnodes":false,"isLeftAligned":false,"id":"E787883B-27DD-472D-9DF4-384CCBDCB95A","pathStyle":{"lineType":"curved","strokeStyle":{"color":"rgba(244, 255, 226, 1.0)","dash":null,"width":4}},"shapeStyle":{"fillColor":"rgba(4, 4, 3, 1.0)","shapeType":"pill","borderStrokeStyle":{"color":"rgba(29, 26, 22, 1.0)","dash":null,"width":2}},"image":null,"title":{"allowToShrinkWidth":true,"maxWidth":300,"text":"<p style='color: rgba(241, 255, 220, 1.000000); font: 24px \"Helvetica Neue\"; text-align: center;  '>help</p>","fontStyle":null},"note":null,"noteIndicatorColor":"rgba(0, 0, 0, 1.0)","nodes":[{"allowNodeStrokeColorVariants":false,"decreasingStrokeWidth":false,"foldedSubnodes":false,"isLeftAligned":false,"id":"75033438-5BB8-4BD2-BF77-407BCD3E09BF","pathStyle":{"lineType":"curved","strokeStyle":{"color":"rgba(104, 255, 109, 1.0)","dash":null,"width":6}},"shapeStyle":{"fillColor":"rgba(29, 26, 22, 1.0)","shapeType":null,"borderStrokeStyle":{"color":"rgba(104, 255, 109, 1.0)","dash":null,"width":4}},"image":null,"title":{"allowToShrinkWidth":true,"maxWidth":300,"text":"<p style=\"text-align: left; \"><a style='color: rgba(255, 254, 216, 1.000000); font: 21px \"Helvetica Neue\";  ' href=\"https://forum.keyboardmaestro.com/latest\" rel=\"nofollow\">forum </a><a style='color: rgba(255, 254, 216, 1.000000); font: 21px \"Apple Color Emoji\";  ' href=\"https://forum.keyboardmaestro.com/latest\" rel=\"nofollow\">💬</a></p>","fontStyle":null},"note":null,"noteIndicatorColor":"rgba(0, 0, 0, 1.0)","nodes":[],"location":{"x":151.55010958710398,"y":-127.88192873303171},"layoutStyle":"manual","task":null},{"allowNodeStrokeColorVariants":false,"decreasingStrokeWidth":false,"foldedSubnodes":false,"isLeftAligned":false,"id":"040A31F6-3C9C-4DC4-B94C-F350DD36CFBA","pathStyle":{"lineType":"curved","strokeStyle":{"color":"rgba(0, 224, 161, 1.0)","dash":null,"width":6}},"shapeStyle":{"fillColor":"rgba(29, 26, 22, 1.0)","shapeType":null,"borderStrokeStyle":{"color":"rgba(0, 224, 161, 1.0)","dash":null,"width":4}},"image":null,"title":{"allowToShrinkWidth":true,"maxWidth":300,"text":"<p style='color: rgba(255, 254, 216, 1.000000); font: 21px \"Helvetica Neue\"; text-align: left;  '><a href=\"https://wiki.keyboardmaestro.com/User_Manual\" rel=\"nofollow\">wiki</a></p>","fontStyle":null},"note":null,"noteIndicatorColor":"rgba(0, 0, 0, 1.0)","nodes":[],"location":{"x":151.55010958710398,"y":-85.88192873303171},"layoutStyle":"manual","task":null}],"location":{"x":10.550109587103975,"y":-121.88192873303171},"layoutStyle":"defaultright","task":null},{"allowNodeStrokeColorVariants":false,"decreasingStrokeWidth":true,"foldedSubnodes":false,"isLeftAligned":false,"id":"0C8B6614-9141-453B-ADDD-F8E03BF0EBF7","pathStyle":{"lineType":"curved","strokeStyle":{"color":"rgba(244, 255, 226, 1.0)","dash":null,"width":4}},"shapeStyle":{"fillColor":"rgba(4, 4, 3, 1.0)","shapeType":"pill","borderStrokeStyle":{"color":"rgba(29, 26, 22, 1.0)","dash":null,"width":2}},"image":null,"title":{"allowToShrinkWidth":true,"maxWidth":300,"text":"<p style='color: rgba(241, 255, 220, 1.000000); font: 24px \"Helvetica Neue\"; text-align: center;  '>interesting</p>","fontStyle":null},"note":null,"noteIndicatorColor":"rgba(0, 0, 0, 1.0)","nodes":[{"allowNodeStrokeColorVariants":false,"decreasingStrokeWidth":false,"foldedSubnodes":false,"isLeftAligned":false,"id":"6E20E35C-C5EA-4C6C-83DA-7E90D1598DB8","pathStyle":{"lineType":"curved","strokeStyle":{"color":"rgba(104, 255, 109, 1.0)","dash":null,"width":6}},"shapeStyle":{"fillColor":"rgba(29, 26, 22, 1.0)","shapeType":null,"borderStrokeStyle":{"color":"rgba(104, 255, 109, 1.0)","dash":null,"width":4}},"image":null,"title":{"allowToShrinkWidth":true,"maxWidth":300,"text":"<p style='color: rgba(255, 254, 216, 1.000000); font: 21px \"Helvetica Neue\"; text-align: left;  '><a href=\"https://forum.keyboardmaestro.com/t/best-macro-list/4118\" rel=\"nofollow\">best macros list</a></p>","fontStyle":null},"note":null,"noteIndicatorColor":"rgba(0, 0, 0, 1.0)","nodes":[],"location":{"x":250.04582386519542,"y":-1.149811412221311},"layoutStyle":"manual","task":null},{"allowNodeStrokeColorVariants":false,"decreasingStrokeWidth":false,"foldedSubnodes":false,"isLeftAligned":false,"id":"3BDF6DAA-B005-46A2-82C2-51B532356F81","pathStyle":{"lineType":"curved","strokeStyle":{"color":"rgba(0, 224, 161, 1.0)","dash":null,"width":6}},"shapeStyle":{"fillColor":"rgba(29, 26, 22, 1.0)","shapeType":null,"borderStrokeStyle":{"color":"rgba(0, 224, 161, 1.0)","dash":null,"width":4}},"image":null,"title":{"allowToShrinkWidth":true,"maxWidth":300,"text":"<p style=\"text-align: left; \"><a style='color: rgba(255, 254, 216, 1.000000); font: 21px \"Helvetica Neue\";  ' href=\"https://github.com/nikitavoloboev/km-macros\" rel=\"nofollow\">km macros collection </a><a style='color: rgba(255, 254, 216, 1.000000); font: 21px \"Apple Color Emoji\";  ' href=\"https://github.com/nikitavoloboev/km-macros\" rel=\"nofollow\">🐙</a></p>","fontStyle":null},"note":null,"noteIndicatorColor":"rgba(0, 0, 0, 1.0)","nodes":[],"location":{"x":250.04582386519542,"y":35.85018858777869},"layoutStyle":"manual","task":null}],"location":{"x":51.045823865195416,"y":4.850188587778689},"layoutStyle":"defaultright","task":null},{"allowNodeStrokeColorVariants":false,"decreasingStrokeWidth":true,"foldedSubnodes":false,"isLeftAligned":false,"id":"FC385A50-962D-409E-85F8-7425CB197521","pathStyle":{"lineType":"curved","strokeStyle":{"color":"rgba(244, 255, 226, 1.0)","dash":null,"width":4}},"shapeStyle":{"fillColor":"rgba(4, 4, 3, 1.0)","shapeType":"pill","borderStrokeStyle":{"color":"rgba(29, 26, 22, 1.0)","dash":null,"width":2}},"image":null,"title":{"allowToShrinkWidth":true,"maxWidth":300,"text":"<p style='color: rgba(241, 255, 220, 1.000000); font: 24px \"Helvetica Neue\"; text-align: center;  '>articles</p>","fontStyle":null},"note":null,"noteIndicatorColor":"rgba(0, 0, 0, 1.0)","nodes":[{"allowNodeStrokeColorVariants":false,"decreasingStrokeWidth":false,"foldedSubnodes":false,"isLeftAligned":false,"id":"EDEDB646-198E-4F33-8390-21B58C655D54","pathStyle":{"lineType":"curved","strokeStyle":{"color":"rgba(104, 255, 109, 1.0)","dash":null,"width":6}},"shapeStyle":{"fillColor":"rgba(29, 26, 22, 1.0)","shapeType":null,"borderStrokeStyle":{"color":"rgba(104, 255, 109, 1.0)","dash":null,"width":4}},"image":null,"title":{"allowToShrinkWidth":true,"maxWidth":300,"text":"<p style=\"text-align: left; \"><a style='color: rgba(255, 254, 216, 1.000000); font: 21px \"Helvetica Neue\";  ' href=\"https://medium.com/@NikitaVoloboev/insta-cloning-ff5f38eb1d32\" rel=\"nofollow\">insta cloning </a><a style='color: rgba(255, 254, 216, 1.000000); font: 21px \"Apple Color Emoji\";  ' href=\"https://medium.com/@NikitaVoloboev/insta-cloning-ff5f38eb1d32\" rel=\"nofollow\">🖋️</a></p>","fontStyle":null},"note":null,"noteIndicatorColor":"rgba(0, 0, 0, 1.0)","nodes":[],"location":{"x":288.3338189592497,"y":151.65082831636914},"layoutStyle":"manual","task":null}],"location":{"x":119.3338189592497,"y":139.15082831636914},"layoutStyle":"defaultright","task":null}],"connections":[{"endNodeID":"90F2E8AB-06E9-4615-8FB1-EB46566DCB4E","startNodeID":"E787883B-27DD-472D-9DF4-384CCBDCB95A","pathStyle":{"lineType":"curved","strokeStyle":{"color":"rgba(144, 124, 104, 1.0)","dash":[5,2],"width":2}},"arrowStyle":{"startArrow":null,"endArrow":"trianglefilled"},"title":{"allowToShrinkWidth":true,"maxWidth":250,"text":"","fontStyle":{"bold":false,"italic":false,"underline":false,"strikethrough":false,"color":"rgba(255, 255, 255, 1.0)","fontName":"HelveticaNeue","fontSize":14,"alignment":"center"}},"wayPointOffset":{"x":-27.2751,"y":-52.4516}},{"endNodeID":"E787883B-27DD-472D-9DF4-384CCBDCB95A","startNodeID":"0C8B6614-9141-453B-ADDD-F8E03BF0EBF7","pathStyle":{"lineType":"curved","strokeStyle":{"color":"rgba(144, 124, 104, 1.0)","dash":[5,2],"width":2}},"arrowStyle":{"startArrow":null,"endArrow":"trianglefilled"},"title":{"allowToShrinkWidth":true,"maxWidth":250,"text":"","fontStyle":{"bold":false,"italic":false,"underline":false,"strikethrough":false,"color":"rgba(255, 255, 255, 1.0)","fontName":"HelveticaNeue","fontSize":14,"alignment":"center"}},"wayPointOffset":{"x":-34.7478,"y":-63.3661}},{"endNodeID":"0C8B6614-9141-453B-ADDD-F8E03BF0EBF7","startNodeID":"FC385A50-962D-409E-85F8-7425CB197521","pathStyle":{"lineType":"curved","strokeStyle":{"color":"rgba(144, 124, 104, 1.0)","dash":[5,2],"width":2}},"arrowStyle":{"startArrow":null,"endArrow":"trianglefilled"},"title":{"allowToShrinkWidth":true,"maxWidth":250,"text":"","fontStyle":{"bold":false,"italic":false,"underline":false,"strikethrough":false,"color":"rgba(255, 255, 255, 1.0)","fontName":"HelveticaNeue","fontSize":14,"alignment":"center"}},"wayPointOffset":{"x":-26.644,"y":-67.1503}}],"ready":true,"trigger":"keyboard maestro app"}