{"token":"rdgKa9yyxeycCFwbFLsJhHxocZzzzzixzyHQhWgk","title":"learn anything - computer graphics - rendering","backgroundColor":"rgba(243, 246, 243, 1.0)","nodes":[{"allowNodeStrokeColorVariants":false,"decreasingStrokeWidth":true,"foldedSubnodes":false,"isLeftAligned":false,"id":"88439C68-7229-4DBA-8D75-6F3CA836D7E2","pathStyle":{"lineType":"curved","strokeStyle":{"color":"rgba(21, 122, 150, 1.0)","dash":null,"width":4}},"shapeStyle":{"fillColor":"rgba(255, 255, 255, 1.0)","shapeType":"roundedrect","borderStrokeStyle":{"color":"rgba(246, 246, 246, 1.0)","dash":null,"width":2}},"image":null,"title":{"allowToShrinkWidth":true,"maxWidth":300,"text":"<p style=\"text-align: center; \"><a style='color: rgba(22, 103, 132, 1.000000); font: 21px \"Helvetica Neue\";  ' href=\"http://www.wikiwand.com/en/Rendering_(computer_graphics)\" rel=\"nofollow\">rendering </a><a style='color: rgba(22, 103, 132, 1.000000); font: 21px \"Apple Color Emoji\";  ' href=\"http://www.wikiwand.com/en/Rendering_(computer_graphics)\" rel=\"nofollow\">🌐</a></p>","fontStyle":null},"note":{"visibleOnCanvas":false,"text":"<p style='color: rgba(0, 0, 0, 1.000000); font: 15px \"Helvetica Neue\";  '>if you think this can be improved in any way</p><p></p><p><a style='color: rgba(0, 0, 0, 1.000000); font: 15px \"Helvetica Neue\";  ' href=\"https://github.com/nikitavoloboev/learn-anything/issues/754\" rel=\"nofollow\">please say</a><span style='color: rgba(0, 0, 0, 1.000000); font: 15px \"Helvetica Neue\";  '> </span><span style='color: rgba(0, 0, 0, 1.000000); font: 15px \"Apple Color Emoji\";  '>💙</span></p>"},"noteIndicatorColor":"rgba(21, 122, 150, 1.0)","nodes":[],"location":{"x":-66.24609375,"y":-285.58877840909093},"layoutStyle":"defaultright","task":null},{"allowNodeStrokeColorVariants":false,"decreasingStrokeWidth":true,"foldedSubnodes":false,"isLeftAligned":false,"id":"3151119E-203E-40ED-985A-47818A7C4B7A","pathStyle":{"lineType":"curved","strokeStyle":{"color":"rgba(21, 122, 150, 1.0)","dash":null,"width":4}},"shapeStyle":{"fillColor":"rgba(255, 255, 255, 1.0)","shapeType":"roundedrect","borderStrokeStyle":{"color":"rgba(246, 246, 246, 1.0)","dash":null,"width":2}},"image":null,"title":{"allowToShrinkWidth":true,"maxWidth":300,"text":"<p style='color: rgba(22, 103, 132, 1.000000); font: 21px \"Helvetica Neue\"; text-align: center;  '>help</p>","fontStyle":null},"note":null,"noteIndicatorColor":"rgba(0, 0, 0, 1.0)","nodes":[{"allowNodeStrokeColorVariants":false,"decreasingStrokeWidth":false,"foldedSubnodes":false,"isLeftAligned":false,"id":"FBDE17DF-DDCA-4162-9CE2-DF50B6E40A3E","pathStyle":{"lineType":"curved","strokeStyle":{"color":"rgba(175, 54, 242, 1.0)","dash":null,"width":6}},"shapeStyle":{"fillColor":"rgba(255, 255, 255, 1.0)","shapeType":null,"borderStrokeStyle":{"color":"rgba(175, 54, 242, 1.0)","dash":null,"width":2}},"image":null,"title":{"allowToShrinkWidth":true,"maxWidth":300,"text":"<p style=\"text-align: left; \"><a style='color: rgba(72, 72, 72, 1.000000); font: 18px \"Helvetica Neue\";  ' href=\"http://www.iquilezles.org/www/articles/outdoorslighting/outdoorslighting.htm\" rel=\"nofollow\">outdoors lighting </a><a style='color: rgba(72, 72, 72, 1.000000); font: 18px \"Apple Color Emoji\";  ' href=\"http://www.iquilezles.org/www/articles/outdoorslighting/outdoorslighting.htm\" rel=\"nofollow\">🖋️</a></p>","fontStyle":null},"note":null,"noteIndicatorColor":"rgba(0, 0, 0, 1.0)","nodes":[],"location":{"x":195.58442679558004,"y":-176.8983943370166},"layoutStyle":"manual","task":null},{"allowNodeStrokeColorVariants":false,"decreasingStrokeWidth":false,"foldedSubnodes":false,"isLeftAligned":false,"id":"6EFB9AEA-7B7C-43EE-8916-E813749D58DB","pathStyle":{"lineType":"curved","strokeStyle":{"color":"rgba(36, 170, 255, 1.0)","dash":null,"width":6}},"shapeStyle":{"fillColor":"rgba(255, 255, 255, 1.0)","shapeType":null,"borderStrokeStyle":{"color":"rgba(36, 170, 255, 1.0)","dash":null,"width":2}},"image":null,"title":{"allowToShrinkWidth":true,"maxWidth":300,"text":"<p style=\"text-align: left; \"><a style='color: rgba(72, 72, 72, 1.000000); font: 18px \"Helvetica Neue\";  ' href=\"https://renderman.pixar.com/resources/RenderMan_20/risSampling.html\" rel=\"nofollow\">sampling </a><a style='color: rgba(72, 72, 72, 1.000000); font: 18px \"Apple Color Emoji\";  ' href=\"https://renderman.pixar.com/resources/RenderMan_20/risSampling.html\" rel=\"nofollow\">🖋️</a></p>","fontStyle":null},"note":null,"noteIndicatorColor":"rgba(0, 0, 0, 1.0)","nodes":[],"location":{"x":195.58442679558004,"y":-136.8983943370166},"layoutStyle":"manual","task":null}],"location":{"x":58.58442679558004,"y":-168.3983943370166},"layoutStyle":"defaultright","task":null},{"allowNodeStrokeColorVariants":false,"decreasingStrokeWidth":true,"foldedSubnodes":false,"isLeftAligned":false,"id":"11EEE6C2-2C6A-41A1-8815-3ED56B4B3E32","pathStyle":{"lineType":"curved","strokeStyle":{"color":"rgba(21, 122, 150, 1.0)","dash":null,"width":4}},"shapeStyle":{"fillColor":"rgba(255, 255, 255, 1.0)","shapeType":"roundedrect","borderStrokeStyle":{"color":"rgba(246, 246, 246, 1.0)","dash":null,"width":2}},"image":null,"title":{"allowToShrinkWidth":true,"maxWidth":300,"text":"<p style='color: rgba(22, 103, 132, 1.000000); font: 21px \"Helvetica Neue\"; text-align: center;  '>tools</p>","fontStyle":null},"note":null,"noteIndicatorColor":"rgba(0, 0, 0, 1.0)","nodes":[{"allowNodeStrokeColorVariants":false,"decreasingStrokeWidth":false,"foldedSubnodes":false,"isLeftAligned":false,"id":"174E8871-9870-4970-9F0D-A0332AE69155","pathStyle":{"lineType":"curved","strokeStyle":{"color":"rgba(175, 54, 242, 1.0)","dash":null,"width":6}},"shapeStyle":{"fillColor":"rgba(255, 255, 255, 1.0)","shapeType":null,"borderStrokeStyle":{"color":"rgba(175, 54, 242, 1.0)","dash":null,"width":2}},"image":null,"title":{"allowToShrinkWidth":true,"maxWidth":300,"text":"<p style='color: rgba(72, 72, 72, 1.000000); font: 18px \"Helvetica Neue\"; text-align: left;  '><a href=\"http://www.madvr.com/\" rel=\"nofollow\">madVR video renderer</a></p>","fontStyle":null},"note":null,"noteIndicatorColor":"rgba(0, 0, 0, 1.0)","nodes":[],"location":{"x":288.1344902682723,"y":-43.206234451612204},"layoutStyle":"manual","task":null}],"location":{"x":146.13449026827232,"y":-57.706234451612204},"layoutStyle":"defaultright","task":null},{"allowNodeStrokeColorVariants":false,"decreasingStrokeWidth":true,"foldedSubnodes":false,"isLeftAligned":false,"id":"F0491650-A6ED-435E-976C-B4BD0B3D1275","pathStyle":{"lineType":"curved","strokeStyle":{"color":"rgba(21, 122, 150, 1.0)","dash":null,"width":4}},"shapeStyle":{"fillColor":"rgba(255, 255, 255, 1.0)","shapeType":"roundedrect","borderStrokeStyle":{"color":"rgba(246, 246, 246, 1.0)","dash":null,"width":2}},"image":null,"title":{"allowToShrinkWidth":true,"maxWidth":300,"text":"<p style=\"text-align: center; \"><a style='color: rgba(22, 103, 132, 1.000000); font: 21px \"Helvetica Neue\";  ' href=\"/id/xXFt6yDav79DvBBUnPbsqtVzQH1fXBqZGRaYRk9D\" rel=\"nofollow\">ray tracing </a><a style='color: rgba(22, 103, 132, 1.000000); font: 21px \"Apple Color Emoji\";  ' href=\"/id/xXFt6yDav79DvBBUnPbsqtVzQH1fXBqZGRaYRk9D\" rel=\"nofollow\">🗺️</a></p>","fontStyle":null},"note":{"visibleOnCanvas":false,"text":"<p style='color: rgba(0, 0, 0, 1.000000); font: 15px \"Helvetica Neue\";  '>is a technique for generating an image by tracing the path of light through pixels in an image plane and simulating the effects of its encounters with virtual objects </p><p></p><p style='color: rgba(0, 0, 0, 1.000000); font: 15px \"Helvetica Neue\";  '>the technique is capable of producing a very high degree of visual realism, usually higher than that of typical scalene rendering methods, but at a greater computational cost</p><p></p><p style='color: rgba(0, 0, 0, 1.000000); font: 15px \"Helvetica Neue\";  '>this makes it best suited for applications where the image can be rendered slowly ahead of time, such as still images and film and television visual effects, and more poorly suited for real-time applications like video games where speed is critical</p><p></p><p style='color: rgba(0, 0, 0, 1.000000); font: 15px \"Helvetica Neue\";  '>it is capable of simulating a wide variety of optical effects, such as reflection and refraction, scattering and dispersion phenomena (such as chromatic aberration)</p><p></p><p style='color: rgba(0, 0, 0, 1.000000); font: 15px \"Helvetica Neue\";  '>it works by tracing a path from an imaginary eye through each pixel in a virtual screen, and calculating the colour of the object visible through it</p>"},"noteIndicatorColor":"rgba(21, 122, 150, 1.0)","nodes":[],"location":{"x":-90.01733220205756,"y":44.62429484069264},"layoutStyle":"defaultright","task":null},{"allowNodeStrokeColorVariants":false,"decreasingStrokeWidth":true,"foldedSubnodes":false,"isLeftAligned":false,"id":"D138BF49-A105-4403-8155-5CC161567C29","pathStyle":{"lineType":"curved","strokeStyle":{"color":"rgba(21, 122, 150, 1.0)","dash":null,"width":4}},"shapeStyle":{"fillColor":"rgba(255, 255, 255, 1.0)","shapeType":"roundedrect","borderStrokeStyle":{"color":"rgba(246, 246, 246, 1.0)","dash":null,"width":2}},"image":null,"title":{"allowToShrinkWidth":true,"maxWidth":300,"text":"<p style=\"text-align: center; \"><a style='color: rgba(22, 103, 132, 1.000000); font: 21px \"Helvetica Neue\";  ' href=\"/id/4urox8eyCpZY5UBmCtGHVZ5vzVLgoeGtKvsgdNTi\" rel=\"nofollow\">path tracing </a><a style='color: rgba(22, 103, 132, 1.000000); font: 21px \"Apple Color Emoji\";  ' href=\"/id/4urox8eyCpZY5UBmCtGHVZ5vzVLgoeGtKvsgdNTi\" rel=\"nofollow\">🗺️</a></p>","fontStyle":null},"note":null,"noteIndicatorColor":"rgba(0, 0, 0, 1.0)","nodes":[],"location":{"x":-455.24198150634766,"y":46.66810131072998},"layoutStyle":"defaultright","task":null},{"allowNodeStrokeColorVariants":false,"decreasingStrokeWidth":true,"foldedSubnodes":false,"isLeftAligned":false,"id":"73104D80-CB39-4DC6-A67F-318FCC353E9C","pathStyle":{"lineType":"curved","strokeStyle":{"color":"rgba(21, 122, 150, 1.0)","dash":null,"width":4}},"shapeStyle":{"fillColor":"rgba(255, 255, 255, 1.0)","shapeType":"roundedrect","borderStrokeStyle":{"color":"rgba(246, 246, 246, 1.0)","dash":null,"width":2}},"image":null,"title":{"allowToShrinkWidth":true,"maxWidth":300,"text":"<p style=\"text-align: center; \"><a style='color: rgba(22, 103, 132, 1.000000); font: 21px \"Helvetica Neue\";  ' href=\"/id/wXM8ybP662spY8LeMcrPDv4edcXgfywKMy1Dj9y9\" rel=\"nofollow\">ray casting </a><a style='color: rgba(22, 103, 132, 1.000000); font: 21px \"Apple Color Emoji\";  ' href=\"/id/wXM8ybP662spY8LeMcrPDv4edcXgfywKMy1Dj9y9\" rel=\"nofollow\">🗺️</a></p>","fontStyle":null},"note":null,"noteIndicatorColor":"rgba(0, 0, 0, 1.0)","nodes":[],"location":{"x":-270.1161595394742,"y":47.82113486842104},"layoutStyle":"defaultright","task":null},{"allowNodeStrokeColorVariants":false,"decreasingStrokeWidth":true,"foldedSubnodes":false,"isLeftAligned":false,"id":"82E0EA78-76A6-428B-B256-DBC3642F0209","pathStyle":{"lineType":"curved","strokeStyle":{"color":"rgba(21, 122, 150, 1.0)","dash":null,"width":4}},"shapeStyle":{"fillColor":"rgba(255, 255, 255, 1.0)","shapeType":"roundedrect","borderStrokeStyle":{"color":"rgba(246, 246, 246, 1.0)","dash":null,"width":2}},"image":null,"title":{"allowToShrinkWidth":true,"maxWidth":300,"text":"<p style=\"text-align: center; \"><a style='color: rgba(22, 103, 132, 1.000000); font: 21px \"Helvetica Neue\";  ' href=\"/id/siNhTVKB2xR1pqNNLph4MjhpQYChdxdwNCFunwyC\" rel=\"nofollow\">foveated rendering </a><a style='color: rgba(22, 103, 132, 1.000000); font: 21px \"Apple Color Emoji\";  ' href=\"/id/siNhTVKB2xR1pqNNLph4MjhpQYChdxdwNCFunwyC\" rel=\"nofollow\">🗺️</a></p>","fontStyle":null},"note":null,"noteIndicatorColor":"rgba(0, 0, 0, 1.0)","nodes":[],"location":{"x":-707.3719329833984,"y":51.45722961425781},"layoutStyle":"defaultright","task":null},{"allowNodeStrokeColorVariants":false,"decreasingStrokeWidth":true,"foldedSubnodes":false,"isLeftAligned":false,"id":"3F9150D9-BD0E-4A9F-9D3D-F9A4CBE30B3B","pathStyle":{"lineType":"curved","strokeStyle":{"color":"rgba(21, 122, 150, 1.0)","dash":null,"width":4}},"shapeStyle":{"fillColor":"rgba(255, 255, 255, 1.0)","shapeType":"roundedrect","borderStrokeStyle":{"color":"rgba(246, 246, 246, 1.0)","dash":null,"width":2}},"image":null,"title":{"allowToShrinkWidth":true,"maxWidth":300,"text":"<p style='color: rgba(22, 103, 132, 1.000000); font: 21px \"Helvetica Neue\"; text-align: center;  '>interesting</p>","fontStyle":null},"note":null,"noteIndicatorColor":"rgba(0, 0, 0, 1.0)","nodes":[{"allowNodeStrokeColorVariants":false,"decreasingStrokeWidth":false,"foldedSubnodes":false,"isLeftAligned":false,"id":"6DD6F7AA-35CF-4271-9199-A45EFE4D13D5","pathStyle":{"lineType":"curved","strokeStyle":{"color":"rgba(175, 54, 242, 1.0)","dash":null,"width":6}},"shapeStyle":{"fillColor":"rgba(255, 255, 255, 1.0)","shapeType":null,"borderStrokeStyle":{"color":"rgba(175, 54, 242, 1.0)","dash":null,"width":2}},"image":null,"title":{"allowToShrinkWidth":true,"maxWidth":300,"text":"<p style=\"text-align: left; \"><a style='color: rgba(72, 72, 72, 1.000000); font: 18px \"Helvetica Neue\";  ' href=\"http://www.playfuljs.com/realistic-terrain-in-130-lines/\" rel=\"nofollow\">realistic terrain in 130 lines </a><a style='color: rgba(72, 72, 72, 1.000000); font: 18px \"Apple Color Emoji\";  ' href=\"http://www.playfuljs.com/realistic-terrain-in-130-lines/\" rel=\"nofollow\">🖋️</a></p>","fontStyle":null},"note":null,"noteIndicatorColor":"rgba(0, 0, 0, 1.0)","nodes":[],"location":{"x":410.8985721982731,"y":70.82819234913768},"layoutStyle":"manual","task":null}],"location":{"x":219.8985721982731,"y":59.32819234913768},"layoutStyle":"defaultright","task":null}],"connections":[{"endNodeID":"88439C68-7229-4DBA-8D75-6F3CA836D7E2","startNodeID":"3151119E-203E-40ED-985A-47818A7C4B7A","pathStyle":{"lineType":"curved","strokeStyle":{"color":"rgba(254, 90, 46, 1.0)","dash":[5,2],"width":2}},"arrowStyle":{"startArrow":null,"endArrow":"trianglefilled"},"title":{"allowToShrinkWidth":true,"maxWidth":250,"text":"","fontStyle":{"bold":false,"italic":false,"underline":false,"strikethrough":false,"color":"rgba(255, 255, 255, 1.0)","fontName":"HelveticaNeue","fontSize":14,"alignment":"center"}},"wayPointOffset":{"x":-43.6652,"y":-57.3452}},{"endNodeID":"F0491650-A6ED-435E-976C-B4BD0B3D1275","startNodeID":"88439C68-7229-4DBA-8D75-6F3CA836D7E2","pathStyle":{"lineType":"curved","strokeStyle":{"color":"rgba(254, 90, 46, 1.0)","dash":[5,2],"width":2}},"arrowStyle":{"startArrow":null,"endArrow":"trianglefilled"},"title":{"allowToShrinkWidth":true,"maxWidth":250,"text":"","fontStyle":{"bold":false,"italic":false,"underline":false,"strikethrough":false,"color":"rgba(255, 255, 255, 1.0)","fontName":"HelveticaNeue","fontSize":14,"alignment":"center"}},"wayPointOffset":{"x":-9.38562,"y":165.107}},{"endNodeID":"3151119E-203E-40ED-985A-47818A7C4B7A","startNodeID":"11EEE6C2-2C6A-41A1-8815-3ED56B4B3E32","pathStyle":{"lineType":"curved","strokeStyle":{"color":"rgba(254, 90, 46, 1.0)","dash":[5,2],"width":2}},"arrowStyle":{"startArrow":null,"endArrow":"trianglefilled"},"title":{"allowToShrinkWidth":true,"maxWidth":250,"text":"","fontStyle":{"bold":false,"italic":false,"underline":false,"strikethrough":false,"color":"rgba(255, 255, 255, 1.0)","fontName":"HelveticaNeue","fontSize":14,"alignment":"center"}},"wayPointOffset":{"x":-45.0251,"y":-55.3461}},{"endNodeID":"D138BF49-A105-4403-8155-5CC161567C29","startNodeID":"88439C68-7229-4DBA-8D75-6F3CA836D7E2","pathStyle":{"lineType":"curved","strokeStyle":{"color":"rgba(254, 90, 46, 1.0)","dash":[5,2],"width":2}},"arrowStyle":{"startArrow":null,"endArrow":"trianglefilled"},"title":{"allowToShrinkWidth":true,"maxWidth":250,"text":"","fontStyle":{"bold":false,"italic":false,"underline":false,"strikethrough":false,"color":"rgba(255, 255, 255, 1.0)","fontName":"HelveticaNeue","fontSize":14,"alignment":"center"}},"wayPointOffset":{"x":-202.498,"y":164.879}},{"endNodeID":"82E0EA78-76A6-428B-B256-DBC3642F0209","startNodeID":"88439C68-7229-4DBA-8D75-6F3CA836D7E2","pathStyle":{"lineType":"curved","strokeStyle":{"color":"rgba(254, 90, 46, 1.0)","dash":[5,2],"width":2}},"arrowStyle":{"startArrow":null,"endArrow":"trianglefilled"},"title":{"allowToShrinkWidth":true,"maxWidth":250,"text":"","fontStyle":{"bold":false,"italic":false,"underline":false,"strikethrough":false,"color":"rgba(255, 255, 255, 1.0)","fontName":"HelveticaNeue","fontSize":14,"alignment":"center"}},"wayPointOffset":{"x":-338.259,"y":158.362}},{"endNodeID":"11EEE6C2-2C6A-41A1-8815-3ED56B4B3E32","startNodeID":"3F9150D9-BD0E-4A9F-9D3D-F9A4CBE30B3B","pathStyle":{"lineType":"curved","strokeStyle":{"color":"rgba(254, 90, 46, 1.0)","dash":[5,2],"width":2}},"arrowStyle":{"startArrow":null,"endArrow":"trianglefilled"},"title":{"allowToShrinkWidth":true,"maxWidth":250,"text":"","fontStyle":{"bold":false,"italic":false,"underline":false,"strikethrough":false,"color":"rgba(255, 255, 255, 1.0)","fontName":"HelveticaNeue","fontSize":14,"alignment":"center"}},"wayPointOffset":{"x":-49.132,"y":-58.5172}},{"endNodeID":"73104D80-CB39-4DC6-A67F-318FCC353E9C","startNodeID":"88439C68-7229-4DBA-8D75-6F3CA836D7E2","pathStyle":{"lineType":"curved","strokeStyle":{"color":"rgba(254, 90, 46, 1.0)","dash":[5,2],"width":2}},"arrowStyle":{"startArrow":null,"endArrow":"trianglefilled"},"title":{"allowToShrinkWidth":true,"maxWidth":250,"text":"","fontStyle":{"bold":false,"italic":false,"underline":false,"strikethrough":false,"color":"rgba(255, 255, 255, 1.0)","fontName":"HelveticaNeue","fontSize":14,"alignment":"left"}},"wayPointOffset":{"x":-112.185,"y":165.455}}],"ready":true,"trigger":"rendering"}