{"token":"EWHvLZs2foxPwdafxLiQBZLRAxepeCEybvzpzGpv","title":"learn anything - health - mindfulness - meditation","backgroundColor":"rgba(243, 246, 243, 1.0)","nodes":[{"allowNodeStrokeColorVariants":false,"decreasingStrokeWidth":true,"foldedSubnodes":false,"isLeftAligned":false,"id":"17B45DEC-DFFB-4FBC-963A-AB4AAB97FCA5","pathStyle":{"lineType":"curved","strokeStyle":{"color":"rgba(21, 122, 150, 1.0)","dash":null,"width":4}},"shapeStyle":{"fillColor":"rgba(255, 255, 255, 1.0)","shapeType":"roundedrect","borderStrokeStyle":{"color":"rgba(246, 246, 246, 1.0)","dash":null,"width":2}},"image":null,"title":{"allowToShrinkWidth":true,"maxWidth":300,"text":"<p style=\"text-align: center; \"><a style='color: rgba(22, 103, 132, 1.000000); font: 21px \"Helvetica Neue\";  ' href=\"http://www.wikiwand.com/en/Meditation\" rel=\"nofollow\">meditation </a><a style='color: rgba(22, 103, 132, 1.000000); font: 21px \"Apple Color Emoji\";  ' href=\"http://www.wikiwand.com/en/Meditation\" rel=\"nofollow\">🌐</a></p>","fontStyle":null},"note":null,"noteIndicatorColor":"rgba(0, 0, 0, 1.0)","nodes":[{"allowNodeStrokeColorVariants":false,"decreasingStrokeWidth":false,"foldedSubnodes":false,"isLeftAligned":false,"id":"B743931A-9646-4B8F-BCA5-5ABE7A54CE9B","pathStyle":{"lineType":"curved","strokeStyle":{"color":"rgba(175, 54, 242, 1.0)","dash":null,"width":6}},"shapeStyle":{"fillColor":"rgba(255, 255, 255, 1.0)","shapeType":null,"borderStrokeStyle":{"color":"rgba(175, 54, 242, 1.0)","dash":null,"width":2}},"image":null,"title":{"allowToShrinkWidth":true,"maxWidth":300,"text":"<p style='color: rgba(72, 72, 72, 1.000000); font: 18px \"Apple Color Emoji\"; text-align: left;  '><a href=\"https://www.reddit.com/r/Meditation/\" rel=\"nofollow\">🤖</a></p>","fontStyle":null},"note":null,"noteIndicatorColor":"rgba(0, 0, 0, 1.0)","nodes":[{"allowNodeStrokeColorVariants":false,"decreasingStrokeWidth":false,"foldedSubnodes":false,"isLeftAligned":false,"id":"EA3342EE-4745-48D9-9BD6-86A138C18344","pathStyle":{"lineType":"curved","strokeStyle":{"color":"rgba(175, 54, 242, 1.0)","dash":null,"width":5}},"shapeStyle":{"fillColor":"rgba(255, 255, 255, 1.0)","shapeType":null,"borderStrokeStyle":{"color":"rgba(175, 54, 242, 1.0)","dash":null,"width":2}},"image":null,"title":{"allowToShrinkWidth":true,"maxWidth":300,"text":"<p style=\"text-align: left; \"><a style='color: rgba(72, 72, 72, 1.000000); font: 18px \"Helvetica Neue\";  ' href=\"https://www.reddit.com/r/Meditation/wiki/faq\" rel=\"nofollow\">wiki </a><a style='color: rgba(72, 72, 72, 1.000000); font: 18px \"Apple Color Emoji\";  ' href=\"https://www.reddit.com/r/Meditation/wiki/faq\" rel=\"nofollow\">🤖</a></p>","fontStyle":null},"note":null,"noteIndicatorColor":"rgba(0, 0, 0, 1.0)","nodes":[],"location":{"x":373.3038903061224,"y":-245.8797034438776},"layoutStyle":"manual","task":null}],"location":{"x":263.3038903061224,"y":-245.8797034438776},"layoutStyle":"manual","task":null}],"location":{"x":41.30389030612241,"y":-259.8797034438776},"layoutStyle":"defaultright","task":null},{"allowNodeStrokeColorVariants":false,"decreasingStrokeWidth":true,"foldedSubnodes":false,"isLeftAligned":false,"id":"07B6E52E-13B4-47C3-86E1-E33D1C20EFDD","pathStyle":{"lineType":"curved","strokeStyle":{"color":"rgba(21, 122, 150, 1.0)","dash":null,"width":4}},"shapeStyle":{"fillColor":"rgba(255, 255, 255, 1.0)","shapeType":"roundedrect","borderStrokeStyle":{"color":"rgba(246, 246, 246, 1.0)","dash":null,"width":2}},"image":null,"title":{"allowToShrinkWidth":true,"maxWidth":300,"text":"<p style='color: rgba(22, 103, 132, 1.000000); font: 21px \"Helvetica Neue\"; text-align: center;  '>basics</p>","fontStyle":null},"note":{"visibleOnCanvas":false,"text":"<p style='color: rgba(0, 0, 0, 1.000000); font: 15px \"Helvetica Neue\";  '>if you think this can be improved in any way</p><p></p><p><a style='color: rgba(0, 0, 0, 1.000000); font: 15px \"Helvetica Neue\";  ' href=\"https://github.com/nikitavoloboev/learn-anything/issues/954\" rel=\"nofollow\">please say</a><span style='color: rgba(0, 0, 0, 1.000000); font: 15px \"Helvetica Neue\";  '> </span><span style='color: rgba(0, 0, 0, 1.000000); font: 15px \"Apple Color Emoji\";  '>💙</span></p>"},"noteIndicatorColor":"rgba(21, 122, 150, 1.0)","nodes":[{"allowNodeStrokeColorVariants":false,"decreasingStrokeWidth":false,"foldedSubnodes":false,"isLeftAligned":false,"id":"5AC23BB2-EDAF-4BC8-BD0B-2F35E23EDDA8","pathStyle":{"lineType":"curved","strokeStyle":{"color":"rgba(175, 54, 242, 1.0)","dash":null,"width":6}},"shapeStyle":{"fillColor":"rgba(255, 255, 255, 1.0)","shapeType":null,"borderStrokeStyle":{"color":"rgba(175, 54, 242, 1.0)","dash":null,"width":2}},"image":null,"title":{"allowToShrinkWidth":true,"maxWidth":300,"text":"<p style=\"text-align: left; \"><a style='color: rgba(72, 72, 72, 1.000000); font: 18px \"Helvetica Neue\";  ' href=\"https://www.reddit.com/r/Meditation/wiki/faq#wiki_how_do_i_begin.3F\" rel=\"nofollow\">1. how do I begin? </a><a style='color: rgba(72, 72, 72, 1.000000); font: 18px \"Apple Color Emoji\";  ' href=\"https://www.reddit.com/r/Meditation/wiki/faq#wiki_how_do_i_begin.3F\" rel=\"nofollow\">🤖</a></p>","fontStyle":null},"note":null,"noteIndicatorColor":"rgba(0, 0, 0, 1.0)","nodes":[],"location":{"x":238.12978316326655,"y":-147.53037308672782},"layoutStyle":"manual","task":null},{"allowNodeStrokeColorVariants":false,"decreasingStrokeWidth":false,"foldedSubnodes":false,"isLeftAligned":false,"id":"1873A79B-7CB8-41E6-816E-08AC9B742816","pathStyle":{"lineType":"curved","strokeStyle":{"color":"rgba(36, 170, 255, 1.0)","dash":null,"width":6}},"shapeStyle":{"fillColor":"rgba(255, 255, 255, 1.0)","shapeType":null,"borderStrokeStyle":{"color":"rgba(36, 170, 255, 1.0)","dash":null,"width":2}},"image":null,"title":{"allowToShrinkWidth":true,"maxWidth":300,"text":"<p style='color: rgba(72, 72, 72, 1.000000); font: 18px \"Helvetica Neue\"; text-align: left;  '><a href=\"http://how-to-meditate.org/\" rel=\"nofollow\">1. how to meditate</a></p>","fontStyle":null},"note":null,"noteIndicatorColor":"rgba(0, 0, 0, 1.0)","nodes":[],"location":{"x":238.12978316326655,"y":-107.53037308672782},"layoutStyle":"manual","task":null},{"allowNodeStrokeColorVariants":false,"decreasingStrokeWidth":false,"foldedSubnodes":false,"isLeftAligned":false,"id":"1AEED1D6-F96F-4F9D-B395-A2C994F23A98","pathStyle":{"lineType":"curved","strokeStyle":{"color":"rgba(255, 189, 10, 1.0)","dash":null,"width":6}},"shapeStyle":{"fillColor":"rgba(255, 255, 255, 1.0)","shapeType":null,"borderStrokeStyle":{"color":"rgba(255, 189, 10, 1.0)","dash":null,"width":2}},"image":null,"title":{"allowToShrinkWidth":true,"maxWidth":300,"text":"<p style='color: rgba(72, 72, 72, 1.000000); font: 18px \"Helvetica Neue\"; text-align: left;  '><a href=\"http://meditation.org.au/class1.asp?mobilecheck=true\" rel=\"nofollow\">1. meditation for beginners</a></p>","fontStyle":null},"note":null,"noteIndicatorColor":"rgba(0, 0, 0, 1.0)","nodes":[],"location":{"x":238.12978316326655,"y":-73.53037308672782},"layoutStyle":"manual","task":null},{"allowNodeStrokeColorVariants":false,"decreasingStrokeWidth":false,"foldedSubnodes":false,"isLeftAligned":false,"id":"9604D910-3A15-4F62-AFE8-84E78BB38440","pathStyle":{"lineType":"curved","strokeStyle":{"color":"rgba(34, 205, 224, 1.0)","dash":null,"width":6}},"shapeStyle":{"fillColor":"rgba(255, 255, 255, 1.0)","shapeType":null,"borderStrokeStyle":{"color":"rgba(34, 205, 224, 1.0)","dash":null,"width":2}},"image":null,"title":{"allowToShrinkWidth":true,"maxWidth":300,"text":"<p style=\"text-align: left; \"><a style='color: rgba(72, 71, 71, 1.000000); font: 18px \"Helvetica Neue\";  ' href=\"http://www.goodreads.com/book/show/25942786-the-mind-illuminated\" rel=\"nofollow\">1. the mind illuminated: a complete meditation guide </a><a style='color: rgba(72, 71, 71, 1.000000); font: 18px \"Apple Color Emoji\";  ' href=\"http://www.goodreads.com/book/show/25942786-the-mind-illuminated\" rel=\"nofollow\">📕</a></p>","fontStyle":null},"note":null,"noteIndicatorColor":"rgba(0, 0, 0, 1.0)","nodes":[],"location":{"x":238.12978316326655,"y":-39.53037308672782},"layoutStyle":"manual","task":null}],"location":{"x":56.12978316326655,"y":-94.03037308672782},"layoutStyle":"defaultright","task":null},{"allowNodeStrokeColorVariants":false,"decreasingStrokeWidth":true,"foldedSubnodes":false,"isLeftAligned":false,"id":"DFF34531-06DF-44AA-BF8E-1289051E97C8","pathStyle":{"lineType":"curved","strokeStyle":{"color":"rgba(21, 122, 150, 1.0)","dash":null,"width":4}},"shapeStyle":{"fillColor":"rgba(255, 255, 255, 1.0)","shapeType":"roundedrect","borderStrokeStyle":{"color":"rgba(246, 246, 246, 1.0)","dash":null,"width":2}},"image":null,"title":{"allowToShrinkWidth":true,"maxWidth":300,"text":"<p style=\"text-align: center; \"><a style='color: rgba(22, 103, 132, 1.000000); font: 21px \"Helvetica Neue\";  ' href=\"/id/PP99d9sP2TBreUtXYvqVgExwucZqC1xuK2P6KnFN\" rel=\"nofollow\">guided meditations </a><a style='color: rgba(22, 103, 132, 1.000000); font: 21px \"Apple Color Emoji\";  ' href=\"/id/PP99d9sP2TBreUtXYvqVgExwucZqC1xuK2P6KnFN\" rel=\"nofollow\">🗺️</a></p>","fontStyle":null},"note":null,"noteIndicatorColor":"rgba(0, 0, 0, 1.0)","nodes":[],"location":{"x":-79.23382537688406,"y":53.53984767587713},"layoutStyle":"defaultright","task":null}],"connections":[{"endNodeID":"07B6E52E-13B4-47C3-86E1-E33D1C20EFDD","startNodeID":"17B45DEC-DFFB-4FBC-963A-AB4AAB97FCA5","pathStyle":{"lineType":"curved","strokeStyle":{"color":"rgba(254, 90, 46, 1.0)","dash":[5,2],"width":2}},"arrowStyle":{"startArrow":null,"endArrow":"trianglefilled"},"title":{"allowToShrinkWidth":true,"maxWidth":250,"text":"","fontStyle":{"bold":false,"italic":false,"underline":false,"strikethrough":false,"color":"rgba(255, 255, 255, 1.0)","fontName":"HelveticaNeue","fontSize":14,"alignment":"center"}},"wayPointOffset":{"x":-9.08705,"y":81.6746}},{"endNodeID":"DFF34531-06DF-44AA-BF8E-1289051E97C8","startNodeID":"07B6E52E-13B4-47C3-86E1-E33D1C20EFDD","pathStyle":{"lineType":"curved","strokeStyle":{"color":"rgba(254, 90, 46, 1.0)","dash":[5,2],"width":2}},"arrowStyle":{"startArrow":null,"endArrow":"trianglefilled"},"title":{"allowToShrinkWidth":true,"maxWidth":250,"text":"","fontStyle":{"bold":false,"italic":false,"underline":false,"strikethrough":false,"color":"rgba(255, 255, 255, 1.0)","fontName":"HelveticaNeue","fontSize":14,"alignment":"left"}},"wayPointOffset":{"x":-45.4318,"y":73.7851}}],"ready":true,"trigger":"meditation"}