{
  "title": "learn anything - machine learning - supervised learning",
  "nodes": [
    {
      "text": "supervised learning",
      "url": "http://www.wikiwand.com/en/Supervised_learning",
      "fx": -146.953125,
      "fy": -183.01171875,
      "category": "wiki"
    },
    {
      "text": "basics",
      "url": "",
      "fx": -76.8125,
      "fy": -50.44752038043475
    },
    {
      "text": "support vector machines  ️",
      "url": "/machine-learning/supervised-learning/support-vector-machines",
      "fx": -277.1434848352036,
      "fy": 92.33165687824089,
      "category": "mindmap"
    }
  ],
  "subnodes": [
    {
      "text": "1. introduction",
      "url": "https://www.youtube.com/watch?v=0dP-YtYZREU",
      "fx": 79.1875,
      "fy": -38.94752038043475,
      "category": "video",
      "color": "rgba(175, 54, 242, 1.0)",
      "parent": "basics"
    }
  ],
  "connections": [
    {
      "source": "supervised learning",
      "target": "basics",
      "curve": {
        "x": -1.42969,
        "y": 65.0321
      }
    },
    {
      "source": "basics",
      "target": "support vector machines  ️",
      "curve": {
        "x": -58.4155,
        "y": 71.3896
      }
    }
  ]
}